multi_rake/__init__.py
multi_rake/algorithm.py
multi_rake/stopwords.py
multi_rake/utils.py
multi_rake-0.0.2.dist-info/LICENSE
multi_rake-0.0.2.dist-info/METADATA
multi_rake-0.0.2.dist-info/WHEEL
multi_rake-0.0.2.dist-info/top_level.txt
multi_rake-0.0.2.dist-info/RECORD
