Metadata-Version: 2.1
Name: multi-rake
Version: 0.0.2
Summary: Multilingual Rapid Automatic Keyword Extraction (RAKE) for Python
Home-page: https://github.com/vgrabovets/multi_rake
Author: Vitaliy Grabovets
Author-email: github@maildepot.net
License: MIT
Keywords: nlp,keywords,rake,keywords extraction
Platform: UNKNOWN
Requires-Python: >=3.5.0
License-File: LICENSE
